CHANGES.rst
MANIFEST.in
README.rst
setup.py
js/__init__.py
js.highcharts.egg-info/PKG-INFO
js.highcharts.egg-info/SOURCES.txt
js.highcharts.egg-info/dependency_links.txt
js.highcharts.egg-info/entry_points.txt
js.highcharts.egg-info/namespace_packages.txt
js.highcharts.egg-info/not-zip-safe
js.highcharts.egg-info/requires.txt
js.highcharts.egg-info/top_level.txt
js/highcharts/__init__.py
js/highcharts/test_highcharts.txt
js/highcharts/resources/highcharts-all.js
js/highcharts/resources/highcharts-more.js
js/highcharts/resources/highcharts-more.src.js
js/highcharts/resources/highcharts.js
js/highcharts/resources/highcharts.src.js
js/highcharts/resources/adapters/mootools-adapter.js
js/highcharts/resources/adapters/mootools-adapter.src.js
js/highcharts/resources/adapters/prototype-adapter.js
js/highcharts/resources/adapters/prototype-adapter.src.js
js/highcharts/resources/adapters/standalone-framework.js
js/highcharts/resources/adapters/standalone-framework.src.js
js/highcharts/resources/modules/annotations.js
js/highcharts/resources/modules/annotations.src.js
js/highcharts/resources/modules/canvas-tools.js
js/highcharts/resources/modules/canvas-tools.src.js
js/highcharts/resources/modules/data.js
js/highcharts/resources/modules/data.src.js
js/highcharts/resources/modules/drilldown.js
js/highcharts/resources/modules/drilldown.src.js
js/highcharts/resources/modules/exporting.js
js/highcharts/resources/modules/exporting.src.js
js/highcharts/resources/modules/funnel.js
js/highcharts/resources/modules/funnel.src.js
js/highcharts/resources/modules/heatmap.js
js/highcharts/resources/modules/heatmap.src.js
js/highcharts/resources/modules/map.js
js/highcharts/resources/modules/map.src.js
js/highcharts/resources/modules/no-data-to-display.js
js/highcharts/resources/modules/no-data-to-display.src.js
js/highcharts/resources/themes/dark-blue.js
js/highcharts/resources/themes/dark-green.js
js/highcharts/resources/themes/gray.js
js/highcharts/resources/themes/grid.js
js/highcharts/resources/themes/skies.js