Metadata-Version: 1.0
Name: js.highcharts
Version: 3.0.7
Summary: Fanstatic packaging of Highcharts
Home-page: UNKNOWN
Author: Andreas Kaiser
Author-email: disko@binary-punks.com
License: BSD
Platform: UNKNOWN
